Workbook

Sheet Daily Sales
A1: Date | B1: Day | C1: Dine-In Sales | D1: Takeout Sales | E1: Delivery Sales | F1: Catering Sales | G1: Gross Sales | H1: Discounts | I1: Net Sales | J1: Tax Collected | K1: Total Revenue | L1: Covers | M1: Avg Check
A2: 46082 | B2: Sun | C2: 1423.18 | D2: 410.02 | E2: 294.7 | F2: 0 | G2: =SUM(C2:F2) -> 2127.9 | H2: 95.99 | I2: =G2-H2 -> 2031.91 | J2: =I2*0.06 -> 121.9146 | K2: =I2+J2 -> 2153.8246 | L2: 77 | M2: =G2/L2 -> 27.635065
A3: 46083 | B3: Mon | C3: 1173.87 | D3: 332.7 | E3: 290.1 | F3: 0 | G3: =SUM(C3:F3) -> 1796.67 | H3: 82.39 | I3: =G3-H3 -> 1714.28 | J3: =I3*0.06 -> 102.8568 | K3: =I3+J3 -> 1817.1368 | L3: 42 | M3: =G3/L3 -> 42.777857
A4: 46084 | B4: Tue | C4: 974.07 | D4: 353.3 | E4: 193.34 | F4: 93.49 | G4: =SUM(C4:F4) -> 1614.2 | H4: 58.81 | I4: =G4-H4 -> 1555.39 | J4: =I4*0.06 -> 93.3234 | K4: =I4+J4 -> 1648.7134 | L4: 73 | M4: =G4/L4 -> 22.112329
A5: 46085 | B5: Wed | C5: 838.18 | D5: 315.37 | E5: 185.8 | F5: 0 | G5: =SUM(C5:F5) -> 1339.35 | H5: 28.3 | I5: =G5-H5 -> 1311.05 | J5: =I5*0.06 -> 78.663 | K5: =I5+J5 -> 1389.713 | L5: 75 | M5: =G5/L5 -> 17.858
A6: 46086 | B6: Thu | C6: 1043.67 | D6: 393.62 | E6: 243.81 | F6: 0 | G6: =SUM(C6:F6) -> 1681.1 | H6: 46.94 | I6: =G6-H6 -> 1634.16 | J6: =I6*0.06 -> 98.0496 | K6: =I6+J6 -> 1732.2096 | L6: 30 | M6: =G6/L6 -> 56.036667
A7: 46087 | B7: Fri | C7: 1440.16 | D7: 458.76 | E7: 483.28 | F7: 0 | G7: =SUM(C7:F7) -> 2382.2 | H7: 71.87 | I7: =G7-H7 -> 2310.33 | J7: =I7*0.06 -> 138.6198 | K7: =I7+J7 -> 2448.9498 | L7: 70 | M7: =G7/L7 -> 34.031429
A8: 46088 | B8: Sat | C8: 1584.41 | D8: 643.01 | E8: 339.38 | F8: 0 | G8: =SUM(C8:F8) -> 2566.8 | H8: 112.08 | I8: =G8-H8 -> 2454.72 | J8: =I8*0.06 -> 147.2832 | K8: =I8+J8 -> 2602.0032 | L8: 65 | M8: =G8/L8 -> 39.489231
A9: 46089 | B9: Sun | C9: 1698.01 | D9: 482.51 | E9: 481.21 | F9: 0 | G9: =SUM(C9:F9) -> 2661.73 | H9: 70.32 | I9: =G9-H9 -> 2591.41 | J9: =I9*0.06 -> 155.4846 | K9: =I9+J9 -> 2746.8946 | L9: 67 | M9: =G9/L9 -> 39.727313
A10: 46090 | B10: Mon | C10: 724.09 | D10: 205.83 | E10: 244.75 | F10: 20.29 | G10: =SUM(C10:F10) -> 1194.96 | H10: 62.54 | I10: =G10-H10 -> 1132.42 | J10: =I10*0.06 -> 67.9452 | K10: =I10+J10 -> 1200.3652 | L10: 35 | M10: =G10/L10 -> 34.141714
A11: 46091 | B11: Tue | C11: 792.89 | D11: 354.35 | E11: 226.21 | F11: 0 | G11: =SUM(C11:F11) -> 1373.45 | H11: 60.53 | I11: =G11-H11 -> 1312.92 | J11: =I11*0.06 -> 78.7752 | K11: =I11+J11 -> 1391.6952 | L11: 80 | M11: =G11/L11 -> 17.168125
A12: 46092 | B12: Wed | C12: 1332.99 | D12: 360.11 | E12: 238.59 | F12: 0 | G12: =SUM(C12:F12) -> 1931.69 | H12: 102.51 | I12: =G12-H12 -> 1829.18 | J12: =I12*0.06 -> 109.7508 | K12: =I12+J12 -> 1938.9308 | L12: 38 | M12: =G12/L12 -> 50.833947
A13: 46093 | B13: Thu | C13: 929.98 | D13: 373.75 | E13: 334.44 | F13: 0 | G13: =SUM(C13:F13) -> 1638.17 | H13: 106.39 | I13: =G13-H13 -> 1531.78 | J13: =I13*0.06 -> 91.9068 | K13: =I13+J13 -> 1623.6868 | L13: 68 | M13: =G13/L13 -> 24.090735
... A32: 46112 | B32: Tue | C32: 1107.16 | D32: 377.73 | E32: 264.98 | F32: 0 | G32: =SUM(C32:F32) -> 1749.87 | H32: 30.01 | I32: =G32-H32 -> 1719.86 | J32: =I32*0.06 -> 103.1916 | K32: =I32+J32 -> 1823.0516 | L32: 85 | M32: =G32/L32 -> 20.586706
A33: TOTALS | C33: =SUM(C2:C32) -> 38363.67 | D33: =SUM(D2:D32) -> 11988.33 | E33: =SUM(E2:E32) -> 9364.19 | F33: =SUM(F2:F32) -> 918.15 | G33: =SUM(G2:G32) -> 60634.34 | H33: =SUM(H2:H32) -> 2096.47 | I33: =SUM(I2:I32) -> 58537.87 | J33: =SUM(J2:J32) -> 3512.2722 | ... L33: =SUM(L2:L32) -> 2231 | M33: =G33/L33 -> 27.1781

Sheet Labor Data
A1: Date | B1: Day | C1: FOH Hours | D1: BOH Hours | E1: Total Hours | F1: FOH Labor $ | G1: BOH Labor $ | H1: Total Labor $ | I1: Net Sales | J1: Labor Cost % | K1: Overtime Hours | L1: OT Cost
A2: 46082 | B2: Sun | C2: 51.5 | D2: 36 | E2: =C2+D2 -> 87.5 | F2: =C2*14.5 -> 746.75 | G2: =D2*16.75 -> 603 | H2: =F2+G2 -> 1349.75 | I2: ='Daily Sales'!I2 -> 2031.91 | J2: =IF(I2=0,0,H2/I2) -> 0.66427647 | K2: 0 | L2: =K2*16.75*1.5 -> 0
A3: 46083 | B3: Mon | C3: 31.4 | D3: 21.8 | E3: =C3+D3 -> 53.2 | F3: =C3*14.5 -> 455.3 | G3: =D3*16.75 -> 365.15 | H3: =F3+G3 -> 820.45 | I3: ='Daily Sales'!I3 -> 1714.28 | J3: =IF(I3=0,0,H3/I3) -> 0.47859743 | K3: 0 | L3: =K3*16.75*1.5 -> 0
A4: 46084 | B4: Tue | C4: 31.1 | D4: 31.9 | E4: =C4+D4 -> 63 | F4: =C4*14.5 -> 450.95 | G4: =D4*16.75 -> 534.325 | H4: =F4+G4 -> 985.275 | I4: ='Daily Sales'!I4 -> 1555.39 | J4: =IF(I4=0,0,H4/I4) -> 0.63345849 | K4: 2.5 | L4: =K4*16.75*1.5 -> 62.8125
A5: 46085 | B5: Wed | C5: 39.3 | D5: 22.5 | E5: =C5+D5 -> 61.8 | F5: =C5*14.5 -> 569.85 | G5: =D5*16.75 -> 376.875 | H5: =F5+G5 -> 946.725 | I5: ='Daily Sales'!I5 -> 1311.05 | J5: =IF(I5=0,0,H5/I5) -> 0.72211205 | K5: 0 | L5: =K5*16.75*1.5 -> 0
A6: 46086 | B6: Thu | C6: 28.4 | D6: 28 | E6: =C6+D6 -> 56.4 | F6: =C6*14.5 -> 411.8 | G6: =D6*16.75 -> 469 | H6: =F6+G6 -> 880.8 | I6: ='Daily Sales'!I6 -> 1634.16 | J6: =IF(I6=0,0,H6/I6) -> 0.53899251 | K6: 2.3 | L6: =K6*16.75*1.5 -> 57.7875
A7: 46087 | B7: Fri | C7: 52.1 | D7: 44.1 | E7: =C7+D7 -> 96.2 | F7: =C7*14.5 -> 755.45 | G7: =D7*16.75 -> 738.675 | H7: =F7+G7 -> 1494.125 | I7: ='Daily Sales'!I7 -> 2310.33 | J7: =IF(I7=0,0,H7/I7) -> 0.64671497 | K7: 0 | L7: =K7*16.75*1.5 -> 0
A8: 46088 | B8: Sat | C8: 53.2 | D8: 43.3 | E8: =C8+D8 -> 96.5 | F8: =C8*14.5 -> 771.4 | G8: =D8*16.75 -> 725.275 | H8: =F8+G8 -> 1496.675 | I8: ='Daily Sales'!I8 -> 2454.72 | J8: =IF(I8=0,0,H8/I8) -> 0.60971312 | K8: 0 | L8: =K8*16.75*1.5 -> 0
A9: 46089 | B9: Sun | C9: 40.9 | D9: 31.1 | E9: =C9+D9 -> 72 | F9: =C9*14.5 -> 593.05 | G9: =D9*16.75 -> 520.925 | H9: =F9+G9 -> 1113.975 | I9: ='Daily Sales'!I9 -> 2591.41 | J9: =IF(I9=0,0,H9/I9) -> 0.42987215 | K9: 0 | L9: =K9*16.75*1.5 -> 0
A10: 46090 | B10: Mon | C10: 31.4 | D10: 20.2 | E10: =C10+D10 -> 51.6 | F10: =C10*14.5 -> 455.3 | G10: =D10*16.75 -> 338.35 | H10: =F10+G10 -> 793.65 | I10: ='Daily Sales'!I10 -> 1132.42 | J10: =IF(I10=0,0,H10/I10) -> 0.70084421 | K10: 0 | L10: =K10*16.75*1.5 -> 0
A11: 46091 | B11: Tue | C11: 31.9 | D11: 24.7 | E11: =C11+D11 -> 56.6 | F11: =C11*14.5 -> 462.55 | G11: =D11*16.75 -> 413.725 | H11: =F11+G11 -> 876.275 | I11: ='Daily Sales'!I11 -> 1312.92 | J11: =IF(I11=0,0,H11/I11) -> 0.66742452 | K11: 3.4 | L11: =K11*16.75*1.5 -> 85.425
A12: 46092 | B12: Wed | C12: 32.5 | D12: 28.9 | E12: =C12+D12 -> 61.4 | F12: =C12*14.5 -> 471.25 | G12: =D12*16.75 -> 484.075 | H12: =F12+G12 -> 955.325 | I12: ='Daily Sales'!I12 -> 1829.18 | J12: =IF(I12=0,0,H12/I12) -> 0.52226954 | K12: 0 | L12: =K12*16.75*1.5 -> 0
A13: 46093 | B13: Thu | C13: 30.6 | D13: 22.3 | E13: =C13+D13 -> 52.9 | F13: =C13*14.5 -> 443.7 | G13: =D13*16.75 -> 373.525 | H13: =F13+G13 -> 817.225 | I13: ='Daily Sales'!I13 -> 1531.78 | J13: =IF(I13=0,0,H13/I13) -> 0.5335133 | K13: 0 | L13: =K13*16.75*1.5 -> 0
... A32: 46112 | B32: Tue | C32: 30 | D32: 24.4 | E32: =C32+D32 -> 54.4 | F32: =C32*14.5 -> 435 | G32: =D32*16.75 -> 408.7 | H32: =F32+G32 -> 843.7 | I32: ='Daily Sales'!I32 -> 1719.86 | J32: =IF(I32=0,0,H32/I32) -> 0.49056319 | K32: 0 | L32: =K32*16.75*1.5 -> 0
A33: TOTALS | C33: =SUM(C2:C32) -> 1209.9 | D33: =SUM(D2:D32) -> 954.3 | E33: =SUM(E2:E32) -> 2164.2 | F33: =SUM(F2:F32) -> 17543.55 | G33: =SUM(G2:G32) -> 15984.525 | H33: =SUM(H2:H32) -> 33528.075 | I33: =SUM(I2:I32) -> 58537.87 | J33: =IF(I33=0,0,H33/I33) -> 0.57275871 | K33: =SUM(K2:K32) -> 25.6 | L33: =SUM(L2:L32) -> 643.2

Sheet Refund Logs
A1: Refund # | B1: Date | C1: Time | D1: Server | E1: Table/Order # | F1: Item(s) | G1: Reason | H1: Refund Amount | I1: Manager Approved | J1: Comp or Void
A2: RF-0001 | B2: 46082 | C2: 15:15 | D2: Carlos R. | E2: T-1 | F2: Grilled Salmon | G2: Wrong table | H2: 40.21 | I2: Mike D. | J2: Comp
A3: RF-0002 | B3: 46085 | C3: 21:45 | D3: Devon P. | E3: T-7 | F3: Dessert Sampler | G3: Customer complaint | H3: 8.58 | I3: Mike D. | J3: Comp
A4: RF-0003 | B4: 46086 | C4: 17:00 | D4: Maria S. | E4: T-27 | F4: House Wine | G4: Long wait | H4: 33.65 | I4: Mike D. | J4: Void
A5: RF-0004 | B5: 46087 | C5: 13:45 | D5: Keisha W. | E5: T-2 | F5: Caesar Salad | G5: Long wait | H5: 28.11 | I5: Mike D. | J5: Comp
A6: RF-0005 | B6: 46087 | C6: 15:30 | D6: Lisa K. | E6: T-15 | F6: Chicken Parm | G6: Long wait | H6: 5.18 | I6: Robert J. | J6: Void
A7: RF-0006 | B7: 46087 | C7: 16:30 | D7: Carlos R. | E7: T-8 | F7: Ribeye Steak | G7: Customer changed mind | H7: 32.53 | I7: Mike D. | J7: Void
A8: RF-0007 | B8: 46087 | C8: 21:00 | D8: James T. | E8: T-11 | F8: Margarita | G8: Customer complaint | H8: 30.85 | I8: Sarah L. | J8: Void
A9: RF-0008 | B9: 46088 | C9: 15:15 | D9: Carlos R. | E9: TO-285 | F9: Ribeye Steak | G9: Customer changed mind | H9: 28.45 | I9: Mike D. | J9: Comp
A10: RF-0009 | B10: 46088 | C10: 15:45 | D10: Keisha W. | E10: TO-384 | F10: Margarita | G10: Missing item | H10: 5.21 | I10: Sarah L. | J10: Void
A11: RF-0010 | B11: 46088 | C11: 21:45 | D11: Carlos R. | E11: TO-212 | F11: Caesar Salad | G11: Cold food | H11: 11.5 | I11: Robert J. | J11: Void
A12: RF-0011 | B12: 46090 | C12: 15:00 | D12: Carlos R. | E12: T-10 | F12: Chicken Parm | G12: Customer left | H12: 18.21 | I12: Mike D. | J12: Comp
A13: RF-0012 | B13: 46090 | C13: 15:45 | D13: Devon P. | E13: T-1 | F13: Dessert Sampler | G13: Customer complaint | H13: 7.77 | I13: Mike D. | J13: Void
... A58: RF-0057 | B58: 46112 | C58: 21:30 | D58: James T. | E58: T-13 | F58: Margarita | G58: Missing item | H58: 12.62 | I58: Sarah L. | J58: Void
G59: TOTAL REFUNDS | H59: =SUM(H2:H58) -> 1324.34
A61: REFUND SUMMARY BY SERVER
A62: Server | B62: Count | C62: Total $ | D62: Avg $ | E62: Void %
A63: Maria S. | B63: =COUNTIF(D2:D58,A63) -> 6 | C63: =SUMIF(D2:D58,A63,H2:H58) -> 154.98 | D63: =IF(B63=0,0,C63/B63) -> 25.83 | E63: =IF(B63=0,0,COUNTIFS(D2:D58,A63,J2:J58,"Void")/B63) -> 0.66666667
A64: James T. | B64: =COUNTIF(D2:D58,A64) -> 5 | C64: =SUMIF(D2:D58,A64,H2:H58) -> 130.72 | D64: =IF(B64=0,0,C64/B64) -> 26.144 | E64: =IF(B64=0,0,COUNTIFS(D2:D58,A64,J2:J58,"Void")/B64) -> 1
A65: Keisha W. | B65: =COUNTIF(D2:D58,A65) -> 7 | C65: =SUMIF(D2:D58,A65,H2:H58) -> 184.59 | D65: =IF(B65=0,0,C65/B65) -> 26.37 | E65: =IF(B65=0,0,COUNTIFS(D2:D58,A65,J2:J58,"Void")/B65) -> 0.71428571
A66: Carlos R. | B66: =COUNTIF(D2:D58,A66) -> 20 | C66: =SUMIF(D2:D58,A66,H2:H58) -> 548.49 | D66: =IF(B66=0,0,C66/B66) -> 27.4245 | E66: =IF(B66=0,0,COUNTIFS(D2:D58,A66,J2:J58,"Void")/B66) -> 0.4
A67: Tanya M. | B67: =COUNTIF(D2:D58,A67) -> 4 | C67: =SUMIF(D2:D58,A67,H2:H58) -> 104.11 | D67: =IF(B67=0,0,C67/B67) -> 26.0275 | E67: =IF(B67=0,0,COUNTIFS(D2:D58,A67,J2:J58,"Void")/B67) -> 0.5
A68: Devon P. | B68: =COUNTIF(D2:D58,A68) -> 10 | C68: =SUMIF(D2:D58,A68,H2:H58) -> 117.72 | D68: =IF(B68=0,0,C68/B68) -> 11.772 | E68: =IF(B68=0,0,COUNTIFS(D2:D58,A68,J2:J58,"Void")/B68) -> 0.2
A69: Lisa K. | B69: =COUNTIF(D2:D58,A69) -> 5 | C69: =SUMIF(D2:D58,A69,H2:H58) -> 83.73 | D69: =IF(B69=0,0,C69/B69) -> 16.746 | E69: =IF(B69=0,0,COUNTIFS(D2:D58,A69,J2:J58,"Void")/B69) -> 0.8

Sheet Menu Mix
A1: Category | B1: Menu Item | C1: Price | D1: Food Cost | E1: Cost % | F1: Units Sold | G1: Gross Revenue | H1: Food Cost Total | I1: Profit | J1: Profit Margin
A2: Appetizers | B2: Wings Platter | C2: 14.99 | D2: 4.2 | E2: =D2/C2 -> 0.28018679 | F2: 70 | G2: =C2*F2 -> 1049.3 | H2: =D2*F2 -> 294 | I2: =G2-H2 -> 755.3 | J2: =IF(G2=0,0,I2/G2) -> 0.71981321
A3: Appetizers | B3: Soup of Day | C3: 7.99 | D3: 1.8 | E3: =D3/C3 -> 0.2252816 | F3: 140 | G3: =C3*F3 -> 1118.6 | H3: =D3*F3 -> 252 | I3: =G3-H3 -> 866.6 | J3: =IF(G3=0,0,I3/G3) -> 0.7747184
A4: Appetizers | B4: Bruschetta | C4: 10.99 | D4: 2.5 | E4: =D4/C4 -> 0.22747953 | F4: 104 | G4: =C4*F4 -> 1142.96 | H4: =D4*F4 -> 260 | I4: =G4-H4 -> 882.96 | J4: =IF(G4=0,0,I4/G4) -> 0.77252047
A5: Appetizers | B5: Calamari | C5: 12.99 | D5: 3.4 | E5: =D5/C5 -> 0.2617398 | F5: 102 | G5: =C5*F5 -> 1324.98 | H5: =D5*F5 -> 346.8 | I5: =G5-H5 -> 978.18 | J5: =IF(G5=0,0,I5/G5) -> 0.7382602
A6: Entrees | B6: Ribeye Steak | C6: 34.99 | D6: 12.5 | E6: =D6/C6 -> 0.35724493 | F6: 320 | G6: =C6*F6 -> 11196.8 | H6: =D6*F6 -> 4000 | I6: =G6-H6 -> 7196.8 | J6: =IF(G6=0,0,I6/G6) -> 0.64275507
A7: Entrees | B7: Grilled Salmon | C7: 28.99 | D7: 9.8 | E7: =D7/C7 -> 0.3380476 | F7: 259 | G7: =C7*F7 -> 7508.41 | H7: =D7*F7 -> 2538.2 | I7: =G7-H7 -> 4970.21 | J7: =IF(G7=0,0,I7/G7) -> 0.6619524
A8: Entrees | B8: Chicken Parm | C8: 19.99 | D8: 5.6 | E8: =D8/C8 -> 0.28014007 | F8: 316 | G8: =C8*F8 -> 6316.84 | H8: =D8*F8 -> 1769.6 | I8: =G8-H8 -> 4547.24 | J8: =IF(G8=0,0,I8/G8) -> 0.71985993
A9: Entrees | B9: Pasta Primavera | C9: 16.99 | D9: 3.9 | E9: =D9/C9 -> 0.22954679 | F9: 40 | G9: =C9*F9 -> 679.6 | H9: =D9*F9 -> 156 | I9: =G9-H9 -> 523.6 | J9: =IF(G9=0,0,I9/G9) -> 0.77045321
A10: Entrees | B10: Burger Deluxe | C10: 15.99 | D10: 4.5 | E10: =D10/C10 -> 0.28142589 | F10: 97 | G10: =C10*F10 -> 1551.03 | H10: =D10*F10 -> 436.5 | I10: =G10-H10 -> 1114.53 | J10: =IF(G10=0,0,I10/G10) -> 0.71857411
A11: Entrees | B11: Fish & Chips | C11: 17.99 | D11: 5.1 | E11: =D11/C11 -> 0.28349083 | F11: 104 | G11: =C11*F11 -> 1870.96 | H11: =D11*F11 -> 530.4 | I11: =G11-H11 -> 1340.56 | J11: =IF(G11=0,0,I11/G11) -> 0.71650917
A12: Entrees | B12: Shrimp Tacos | C12: 18.99 | D12: 6.2 | E12: =D12/C12 -> 0.32648763 | F12: 136 | G12: =C12*F12 -> 2582.64 | H12: =D12*F12 -> 843.2 | I12: =G12-H12 -> 1739.44 | J12: =IF(G12=0,0,I12/G12) -> 0.67351237
A13: Entrees | B13: Lobster Roll | C13: 26.99 | D13: 10.5 | E13: =D13/C13 -> 0.38903298 | F13: 108 | G13: =C13*F13 -> 2914.92 | H13: =D13*F13 -> 1134 | I13: =G13-H13 -> 1780.92 | J13: =IF(G13=0,0,I13/G13) -> 0.61096702
... A24: Beverages | B24: Coffee | C24: 3.99 | D24: 0.5 | E24: =D24/C24 -> 0.12531328 | F24: 145 | G24: =C24*F24 -> 578.55 | H24: =D24*F24 -> 72.5 | I24: =G24-H24 -> 506.05 | J24: =IF(G24=0,0,I24/G24) -> 0.87468672
E25: TOTALS | F25: =SUM(F2:F24) -> 3152 | G25: =SUM(G2:G24) -> 50136.48 | H25: =SUM(H2:H24) -> 14878.9 | I25: =SUM(I2:I24) -> 35257.58 | J25: =IF(G25=0,0,I25/G25) -> 0.70323206

Sheet Time Cards
A1: Employee ID | B1: Employee Name | C1: Role | D1: Date | E1: Clock In | F1: Clock Out | G1: Scheduled Hrs | H1: Actual Hrs | I1: Overtime Hrs | J1: Hourly Rate | K1: Regular Pay | L1: OT Pay | M1: Total Pay
A2: E001 | B2: Maria Sanchez | C2: Server | D2: 46082 | E2: 16:15 | F2: 22:54 | G2: 7 | H2: 6.9 | I2: 0 | J2: 14.5 | K2: =IF(H2>8,8,H2)*J2 -> 100.05 | L2: =I2*J2*1.5 -> 0 | M2: =K2+L2 -> 100.05
A3: E001 | B3: Maria Sanchez | C3: Server | D3: 46084 | E3: 17:15 | F3: 25:05 | G3: 8 | H3: 8.1 | I3: 0.1 | J3: 14.5 | K3: =IF(H3>8,8,H3)*J3 -> 116 | L3: =I3*J3*1.5 -> 2.175 | M3: =K3+L3 -> 118.175
A4: E001 | B4: Maria Sanchez | C4: Server | D4: 46085 | E4: 17:30 | F4: 23:24 | G4: 6 | H4: 6.4 | I4: 0 | J4: 14.5 | K4: =IF(H4>8,8,H4)*J4 -> 92.8 | L4: =I4*J4*1.5 -> 0 | M4: =K4+L4 -> 92.8
A5: E001 | B5: Maria Sanchez | C5: Server | D5: 46087 | E5: 16:00 | F5: 22:42 | G5: 7 | H5: 6.7 | I5: 0 | J5: 14.5 | K5: =IF(H5>8,8,H5)*J5 -> 97.15 | L5: =I5*J5*1.5 -> 0 | M5: =K5+L5 -> 97.15
A6: E001 | B6: Maria Sanchez | C6: Server | D6: 46088 | E6: 10:30 | F6: 19:24 | G6: 8 | H6: 9.4 | I6: 1.4 | J6: 14.5 | K6: =IF(H6>8,8,H6)*J6 -> 116 | L6: =I6*J6*1.5 -> 30.45 | M6: =K6+L6 -> 146.45
A7: E001 | B7: Maria Sanchez | C7: Server | D7: 46089 | E7: 16:00 | F7: 22:12 | G7: 6 | H7: 6.2 | I7: 0 | J7: 14.5 | K7: =IF(H7>8,8,H7)*J7 -> 89.9 | L7: =I7*J7*1.5 -> 0 | M7: =K7+L7 -> 89.9
A8: E001 | B8: Maria Sanchez | C8: Server | D8: 46090 | E8: 16:15 | F8: 24:00 | G8: 8 | H8: 8 | I8: 0 | J8: 14.5 | K8: =IF(H8>8,8,H8)*J8 -> 116 | L8: =I8*J8*1.5 -> 0 | M8: =K8+L8 -> 116
A9: E001 | B9: Maria Sanchez | C9: Server | D9: 46091 | E9: 16:15 | F9: 22:47 | G9: 7 | H9: 6.8 | I9: 0 | J9: 14.5 | K9: =IF(H9>8,8,H9)*J9 -> 98.6 | L9: =I9*J9*1.5 -> 0 | M9: =K9+L9 -> 98.6
A10: E001 | B10: Maria Sanchez | C10: Server | D10: 46092 | E10: 11:15 | F10: 18:42 | G10: 8 | H10: 7.7 | I10: 0 | J10: 14.5 | K10: =IF(H10>8,8,H10)*J10 -> 111.65 | L10: =I10*J10*1.5 -> 0 | M10: =K10+L10 -> 111.65
A11: E001 | B11: Maria Sanchez | C11: Server | D11: 46093 | E11: 17:00 | F11: 23:54 | G11: 6 | H11: 6.9 | I11: 0 | J11: 14.5 | K11: =IF(H11>8,8,H11)*J11 -> 100.05 | L11: =I11*J11*1.5 -> 0 | M11: =K11+L11 -> 100.05
A12: E001 | B12: Maria Sanchez | C12: Server | D12: 46096 | E12: 10:15 | F12: 18:11 | G12: 7 | H12: 8.2 | I12: 0.2 | J12: 14.5 | K12: =IF(H12>8,8,H12)*J12 -> 116 | L12: =I12*J12*1.5 -> 4.35 | M12: =K12+L12 -> 120.35
A13: E001 | B13: Maria Sanchez | C13: Server | D13: 46097 | E13: 11:00 | F13: 18:12 | G13: 6 | H13: 7.2 | I13: 0 | J13: 14.5 | K13: =IF(H13>8,8,H13)*J13 -> 104.4 | L13: =I13*J13*1.5 -> 0 | M13: =K13+L13 -> 104.4
... A284: E012 | B284: Jamal Brown | C284: Server | D284: 46112 | E284: 10:00 | F284: 18:05 | G284: 7 | H284: 8.1 | I284: 0.1 | J284: 14.5 | K284: =IF(H284>8,8,H284)*J284 -> 116 | L284: =I284*J284*1.5 -> 2.175 | M284: =K284+L284 -> 118.175
F285: TOTALS | G285: =SUM(G2:G284) -> 1988 | H285: =SUM(H2:H284) -> 2147.6 | I285: =SUM(I2:I284) -> 90.5 | K285: =SUM(K2:K284) -> 33419.575 | L285: =SUM(L2:L284) -> 2235.0375 | M285: =SUM(M2:M284) -> 35654.613
